p5core/README_user.md
p5core/__init__.py
p5core/__main__.py
p5core/encryptedcontainer.py
p5core/html.py
p5core/install.py
p5core/install_helpers.py
p5core/template_html.py
p5core-0.7.0.dist-info/entry_points.txt
p5core-0.7.0.dist-info/WHEEL
p5core-0.7.0.dist-info/METADATA
p5core-0.7.0.dist-info/RECORD
