Metadata-Version: 2.1
Name: p5core
Version: 0.7.0
Summary: Programmer en Python comme un Pro Par la Pratique
Home-page: https://github.com/vpoulailleau/p5
License: Proprietary
Keywords: learn,Python,practical,exercices
Author: Vincent Poulailleau
Author-email: vpoulailleau@gmail.com
Requires-Python: >=3.7,<4.0
Classifier: License :: Other/Proprietary License
Classifier: Operating System :: OS Independent
Classifier: Programming Language :: Python :: 3
Classifier: Programming Language :: Python :: 3.7
Classifier: Programming Language :: Python :: 3.8
Classifier: Programming Language :: Python :: 3.9
Requires-Dist: py7zr (>=0.11.0,<0.12.0)
Requires-Dist: requests (>=2.20.0,<3.0.0)
Requires-Dist: simplelogging (>=0.10,<0.12)
Project-URL: Documentation, https://github.com/vpoulailleau/p5
Project-URL: Repository, https://github.com/vpoulailleau/p5
